pylinearalgebra/__init__.py
pylinearalgebra/matrix_multiplication.py
pylinearalgebra/matrix_operations.py
pylinearalgebra-0.0.1.dist-info/LICENSE.txt
pylinearalgebra-0.0.1.dist-info/METADATA
pylinearalgebra-0.0.1.dist-info/WHEEL
pylinearalgebra-0.0.1.dist-info/top_level.txt
pylinearalgebra-0.0.1.dist-info/RECORD
