Metadata-Version: 2.1
Name: pylinearalgebra
Version: 0.0.1
Summary: A Linear algebra package
Home-page: https://github.com/PyLinearAlgebra/pylinearalgebra
Author: Linear Algebra
Author-email: cmstatistics2010@gmail.com
License: UNKNOWN
Platform: UNKNOWN
Classifier: Programming Language :: Python :: 3
Classifier: License :: OSI Approved :: MIT License
Classifier: Operating System :: OS Independent
Requires-Python: >=3.6
